Metadata-Version: 2.1
Name: to7m-putil
Version: 0.0.0
Summary: Library for dealing with processes.
Home-page: https://gitlab.com/to7m/to7m_putil.git
Author: to7m
Author-email: mail@to7m.lol
License: UNKNOWN
Platform: UNKNOWN
Classifier: Programming Language :: Python :: 3
Classifier: License :: OSI Approved :: GNU Affero General Public License v3
Classifier: Operating System :: POSIX :: Linux
Requires-Python: >=3.10
License-File: LICENSE.TXT
Requires-Dist: psutil (<6,>=5.9.0)
